JTBrix/__init__.py
JTBrix/app.py
JTBrix/cli.py
JTBrix/run.py
JTBrix/screen_config.py
JTBrix/data/config.yml
JTBrix/data/results/Test_data.csv
JTBrix/data/results/Test_data.json
JTBrix/data/results/Test_data.txt
JTBrix/data/results/Test_data.yml
JTBrix/data/static/images/FB.png
JTBrix/data/static/images/GI.png
JTBrix/data/static/images/GT.png
JTBrix/data/static/images/TB.png
JTBrix/data/static/videos/FB.mp4
JTBrix/data/static/videos/GI.mp4
JTBrix/data/static/videos/GT.mp4
JTBrix/data/static/videos/TB.mp4
JTBrix/experiment/__init__.py
JTBrix/experiment/run_experiment.py
JTBrix/io/__init__.py
JTBrix/io/saving.py
JTBrix/questionnaire/__init__.py
JTBrix/questionnaire/screens.py
JTBrix/templates/question_screen.html
JTBrix/templates/text_input.html
JTBrix/templates/video_screen.html
JTBrix/ui/__init__.py
JTBrix/ui/main.py
JTBrix/utils/Test.ipynb
JTBrix/utils/__init__.py
JTBrix/utils/config.py
JTBrix/utils/env_info.py
JTBrix/utils/paths.py
JTBrix/utils/port.py
JTBrix/utils/results.py
jtbrix-0.0.7.dist-info/licenses/AUTHORS.rst
jtbrix-0.0.7.dist-info/licenses/LICENSE
jtbrix-0.0.7.dist-info/METADATA
jtbrix-0.0.7.dist-info/WHEEL
jtbrix-0.0.7.dist-info/top_level.txt
jtbrix-0.0.7.dist-info/RECORD
