Metadata-Version: 2.4
Name: JTBrix
Version: 0.0.7
Summary: JTBrix is a modular Python package for running behavioral experiments in psychology.
Author-email: Amid Nayerhoda <Nayerhoda@infn.it>
Maintainer-email: Amid Nayerhoda <Nayerhoda@infn.it>
License: MIT license
Project-URL: bugs, https://github.com/amidn/JTBrix/issues
Project-URL: changelog, https://github.com/amidn/JTBrix/blob/master/changelog.md
Project-URL: homepage, https://github.com/amidn/JTBrix
License-File: LICENSE
License-File: AUTHORS.rst
Requires-Dist: numpy
Requires-Dist: typer
Requires-Dist: flask==3.1.0
Provides-Extra: dev
Requires-Dist: coverage; extra == "dev"
Requires-Dist: mypy; extra == "dev"
Requires-Dist: pytest; extra == "dev"
Requires-Dist: ruff; extra == "dev"
Requires-Dist: pyyaml; extra == "dev"
Dynamic: license-file
